djdt_flamegraph/__init__.py
djdt_flamegraph/djdt_flamegraph.py
djdt_flamegraph/flamegraph.pl
djdt_flamegraph/flamegraph.py
djdt_flamegraph-0.2.13.dist-info/LICENSE
djdt_flamegraph-0.2.13.dist-info/METADATA
djdt_flamegraph-0.2.13.dist-info/WHEEL
djdt_flamegraph-0.2.13.dist-info/top_level.txt
djdt_flamegraph-0.2.13.dist-info/RECORD
