Metadata-Version: 2.1
Name: djdt-flamegraph
Version: 0.2.13
Summary: Flamegraphs for Django Debug Toolbar
Home-page: https://github.com/23andme/djdt-flamegraph
Author: Bo Lopker
Author-email: blopker@23andme.com
License: MIT
Keywords: djdt_flamegraph
Platform: UNKNOWN
Classifier: Development Status :: 4 - Beta
Classifier: Intended Audience :: Developers
Classifier: Natural Language :: English
Classifier: Programming Language :: Python :: 2
Classifier: Programming Language :: Python :: 2.7
Classifier: Programming Language :: Python :: 3
Classifier: Programming Language :: Python :: 3.4
